keyenv/__init__.py
keyenv/__version__.py
keyenv/constvars.py
keyenv/core.py
keyenv/utils.py
keyenv-0.1.0.dist-info/METADATA
keyenv-0.1.0.dist-info/WHEEL
keyenv-0.1.0.dist-info/RECORD
