Metadata-Version: 2.1
Name: keyenv
Version: 0.1.0
Summary: Store and load secret key-value pairs from a local cache
Home-page: https://github.com/andreakiro/python-keyenv
License: MIT
Keywords: api,keys,env,cache,configurations,python
Author: Andrea Pinto
Author-email: andreakiro.pinto@gmail.com
Requires-Python: >=3.8,<4.0
Classifier: License :: OSI Approved :: MIT License
Classifier: Programming Language :: Python :: 3
Classifier: Programming Language :: Python :: 3.8
Classifier: Programming Language :: Python :: 3.9
Classifier: Programming Language :: Python :: 3.10
Classifier: Programming Language :: Python :: 3.11
Requires-Dist: python-dotenv (==1.0.0)
Project-URL: Repository, https://github.com/andreakiro/python-keyenv
